Lab1/adder_sync/top.v
module top #(
   parameter BITWIDTH = 4
)(
	input clk,
	input [BITWIDTH-1:0] in_a,
	input [BITWIDTH-1:0] in_b,
	output reg [BITWIDTH-1:0] out_d,
	output reg out_ovf
);
	always @ (posedge clk) begin
		{out_ovf, out_d} <= in_a + in_b;
	end
endmodule

Lab1/adder_sync/top.vcd
$version Generated by VerilatedVcd $end
$date Tue Mar 21 18:30:30 2023
 $end
$timescale   1ps $end

 $scope module TOP $end
  $var wire  1 # clk $end
  $var wire  4 $ in_a [3:0] $end
  $var wire  4 % in_b [3:0] $end
  $var wire  4 & out_d [3:0] $end
  $var wire  1 ' out_ovf $end
  $scope module top $end
   $var wire 32 ( BITWIDTH [31:0] $end
   $var wire  1 # clk $end
   $var wire  4 $ in_a [3:0] $end
   $var wire  4 % in_b [3:0] $end
   $var wire  4 & out_d [3:0] $end
   $var wire  1 ' out_ovf $end
  $upscope $end
 $upscope $end
$enddefinitions $end


#0
0#
b0000 $
b0000 %
b0000 &
0'
b00000000000000000000000000000100 (
#1
1#
#2
0#
#3
1#
b0001 %
#4
0#
#5
1#
b0010 %
b0001 &
#6
0#
#7
1#
b0011 %
b0010 &
#8
0#
#9
1#
b0100 %
b0011 &
#10
0#
#11
1#
b0101 %
b0100 &
#12
0#
#13
1#
b0110 %
b0101 &
#14
0#
#15
1#
b0111 %
b0110 &
#16
0#
#17
1#
b1000 %
b0111 &
#18
0#
#19
1#
b1001 %
b1000 &
#20
0#
#21
1#
b1010 %
b1001 &
#22
0#
#23
1#
b1011 %
b1010 &
#24
0#
#25
1#
b1100 %
b1011 &
#26
0#
#27
1#
b1101 %
b1100 &
#28
0#
#29
1#
b1110 %
b1101 &
#30
0#
#31
1#
b1111 %
b1110 &
#32
0#
#33
1#
b0001 $
b0000 %
b1111 &
#34
0#
#35
1#
b0001 %
b0001 &
#36
0#
#37
1#
b0010 %
b0010 &
#38
0#
#39
1#
b0011 %
b0011 &
#40
0#
#41
1#
b0100 %
b0100 &
#42
0#
#43
1#
b0101 %
b0101 &
#44
0#
#45
1#
b0110 %
b0110 &
#46
0#
#47
1#
b0111 %
b0111 &
#48
0#
#49
1#
b1000 %
b1000 &
#50
0#
#51
1#
b1001 %
b1001 &
#52
0#
#53
1#
b1010 %
b1010 &
#54
0#
#55
1#
b1011 %
b1011 &
#56
0#
#57
1#
b1100 %
b1100 &
#58
0#
#59
1#
b1101 %
b1101 &
#60
0#
#61
1#
b1110 %
b1110 &
#62
0#
#63
1#
b1111 %
b1111 &
#64
0#
#65
1#
b0010 $
b0000 %
b0000 &
1'
#66
0#
#67
1#
b0001 %
b0010 &
0'
#68
0#
#69
1#
b0010 %
b0011 &
#70
0#
#71
1#
b0011 %
b0100 &
#72
0#
#73
1#
b0100 %
b0101 &
#74
0#
#75
1#
b0101 %
b0110 &
#76
0#
#77
1#
b0110 %
b0111 &
#78
0#
#79
1#
b0111 %
b1000 &
#80
0#
#81
1#
b1000 %
b1001 &
#82
0#
#83
1#
b1001 %
b1010 &
#84
0#
#85
1#
b1010 %
b1011 &
#86
0#
#87
1#
b1011 %
b1100 &
#88
0#
#89
1#
b1100 %
b1101 &
#90
0#
#91
1#
b1101 %
b1110 &
#92
0#
#93
1#
b1110 %
b1111 &
#94
0#
#95
1#
b1111 %
b0000 &
1'
#96
0#
#97
1#
b0011 $
b0000 %
b0001 &
#98
0#
#99
1#
b0001 %
b0011 &
0'
#100
0#
#101
1#
b0010 %
b0100 &
#102
0#
#103
1#
b0011 %
b0101 &
#104
0#
#105
1#
b0100 %
b0110 &
#106
0#
#107
1#
b0101 %
b0111 &
#108
0#
#109
1#
b0110 %
b1000 &
#110
0#
#111
1#
b0111 %
b1001 &
#112
0#
#113
1#
b1000 %
b1010 &
#114
0#
#115
1#
b1001 %
b1011 &
#116
0#
#117
1#
b1010 %
b1100 &
#118
0#
#119
1#
b1011 %
b1101 &
#120
0#
#121
1#
b1100 %
b1110 &
#122
0#
#123
1#
b1101 %
b1111 &
#124
0#
#125
1#
b1110 %
b0000 &
1'
#126
0#
#127
1#
b1111 %
b0001 &
#128
0#
#129
1#
b0100 $
b0000 %
b0010 &
#130
0#
#131
1#
b0001 %
b0100 &
0'
#132
0#
#133
1#
b0010 %
b0101 &
#134
0#
#135
1#
b0011 %
b0110 &
#136
0#
#137
1#
b0100 %
b0111 &
#138
0#
#139
1#
b0101 %
b1000 &
#140
0#
#141
1#
b0110 %
b1001 &
#142
0#
#143
1#
b0111 %
b1010 &
#144
0#
#145
1#
b1000 %
b1011 &
#146
0#
#147
1#
b1001 %
b1100 &
#148
0#
#149
1#
b1010 %
b1101 &
#150
0#
#151
1#
b1011 %
b1110 &
#152
0#
#153
1#
b1100 %
b1111 &
#154
0#
#155
1#
b1101 %
b0000 &
1'
#156
0#
#157
1#
b1110 %
b0001 &
#158
0#
#159
1#
b1111 %
b0010 &
#160
0#
#161
1#
b0101 $
b0000 %
b0011 &
#162
0#
#163
1#
b0001 %
b0101 &
0'
#164
0#
#165
1#
b0010 %
b0110 &
#166
0#
#167
1#
b0011 %
b0111 &
#168
0#
#169
1#
b0100 %
b1000 &
#170
0#
#171
1#
b0101 %
b1001 &
#172
0#
#173
1#
b0110 %
b1010 &
#174
0#
#175
1#
b0111 %
b1011 &
#176
0#
#177
1#
b1000 %
b1100 &
#178
0#
#179
1#
b1001 %
b1101 &
#180
0#
#181
1#
b1010 %
b1110 &
#182
0#
#183
1#
b1011 %
b1111 &
#184
0#
#185
1#
b1100 %
b0000 &
1'
#186
0#
#187
1#
b1101 %
b0001 &
#188
0#
#189
1#
b1110 %
b0010 &
#190
0#
#191
1#
b1111 %
b0011 &
#192
0#
#193
1#
b0110 $
b0000 %
b0100 &
#194
0#
#195
1#
b0001 %
b0110 &
0'
#196
0#
#197
1#
b0010 %
b0111 &
#198
0#
#199
1#
b0011 %
b1000 &
#200
0#
#201
1#
b0100 %
b1001 &
#202
0#
#203
1#
b0101 %
b1010 &
#204
0#
#205
1#
b0110 %
b1011 &
#206
0#
#207
1#
b0111 %
b1100 &
#208
0#
#209
1#
b1000 %
b1101 &
#210
0#
#211
1#
b1001 %
b1110 &
#212
0#
#213
1#
b1010 %
b1111 &
#214
0#
#215
1#
b1011 %
b0000 &
1'
#216
0#
#217
1#
b1100 %
b0001 &
#218
0#
#219
1#
b1101 %
b0010 &
#220
0#
#221
1#
b1110 %
b0011 &
#222
0#
#223
1#
b1111 %
b0100 &
#224
0#
#225
1#
b0111 $
b0000 %
b0101 &
#226
0#
#227
1#
b0001 %
b0111 &
0'
#228
0#
#229
1#
b0010 %
b1000 &
#230
0#
#231
1#
b0011 %
b1001 &
#232
0#
#233
1#
b0100 %
b1010 &
#234
0#
#235
1#
b0101 %
b1011 &
#236
0#
#237
1#
b0110 %
b1100 &
#238
0#
#239
1#
b0111 %
b1101 &
#240
0#
#241
1#
b1000 %
b1110 &
#242
0#
#243
1#
b1001 %
b1111 &
#244
0#
#245
1#
b1010 %
b0000 &
1'
#246
0#
#247
1#
b1011 %
b0001 &
#248
0#
#249
1#
b1100 %
b0010 &
#250
0#
#251
1#
b1101 %
b0011 &
#252
0#
#253
1#
b1110 %
b0100 &
#254
0#
#255
1#
b1111 %
b0101 &
#256
0#
#257
1#
b1000 $
b0000 %
b0110 &
#258
0#
#259
1#
b0001 %
b1000 &
0'
#260
0#
#261
1#
b0010 %
b1001 &
#262
0#
#263
1#
b0011 %
b1010 &
#264
0#
#265
1#
b0100 %
b1011 &
#266
0#
#267
1#
b0101 %
b1100 &
#268
0#
#269
1#
b0110 %
b1101 &
#270
0#
#271
1#
b0111 %
b1110 &
#272
0#
#273
1#
b1000 %
b1111 &
#274
0#
#275
1#
b1001 %
b0000 &
1'
#276
0#
#277
1#
b1010 %
b0001 &
#278
0#
#279
1#
b1011 %
b0010 &
#280
0#
#281
1#
b1100 %
b0011 &
#282
0#
#283
1#
b1101 %
b0100 &
#284
0#
#285
1#
b1110 %
b0101 &
#286
0#
#287
1#
b1111 %
b0110 &
#288
0#
#289
1#
b1001 $
b0000 %
b0111 &
#290
0#
#291
1#
b0001 %
b1001 &
0'
#292
0#
#293
1#
b0010 %
b1010 &
#294
0#
#295
1#
b0011 %
b1011 &
#296
0#
#297
1#
b0100 %
b1100 &
#298
0#
#299
1#
b0101 %
b1101 &
#300
0#
#301
1#
b0110 %
b1110 &
#302
0#
#303
1#
b0111 %
b1111 &
#304
0#
#305
1#
b1000 %
b0000 &
1'
#306
0#
#307
1#
b1001 %
b0001 &
#308
0#
#309
1#
b1010 %
b0010 &
#310
0#
#311
1#
b1011 %
b0011 &
#312
0#
#313
1#
b1100 %
b0100 &
#314
0#
#315
1#
b1101 %
b0101 &
#316
0#
#317
1#
b1110 %
b0110 &
#318
0#
#319
1#
b1111 %
b0111 &
#320
0#
#321
1#
b1010 $
b0000 %
b1000 &
#322
0#
#323
1#
b0001 %
b1010 &
0'
#324
0#
#325
1#
b0010 %
b1011 &
#326
0#
#327
1#
b0011 %
b1100 &
#328
0#
#329
1#
b0100 %
b1101 &
#330
0#
#331
1#
b0101 %
b1110 &
#332
0#
#333
1#
b0110 %
b1111 &
#334
0#
#335
1#
b0111 %
b0000 &
1'
#336
0#
#337
1#
b1000 %
b0001 &
#338
0#
#339
1#
b1001 %
b0010 &
#340
0#
#341
1#
b1010 %
b0011 &
#342
0#
#343
1#
b1011 %
b0100 &
#344
0#
#345
1#
b1100 %
b0101 &
#346
0#
#347
1#
b1101 %
b0110 &
#348
0#
#349
1#
b1110 %
b0111 &
#350
0#
#351
1#
b1111 %
b1000 &
#352
0#
#353
1#
b1011 $
b0000 %
b1001 &
#354
0#
#355
1#
b0001 %
b1011 &
0'
#356
0#
#357
1#
b0010 %
b1100 &
#358
0#
#359
1#
b0011 %
b1101 &
#360
0#
#361
1#
b0100 %
b1110 &
#362
0#
#363
1#
b0101 %
b1111 &
#364
0#
#365
1#
b0110 %
b0000 &
1'
#366
0#
#367
1#
b0111 %
b0001 &
#368
0#
#369
1#
b1000 %
b0010 &
#370
0#
#371
1#
b1001 %
b0011 &
#372
0#
#373
1#
b1010 %
b0100 &
#374
0#
#375
1#
b1011 %
b0101 &
#376
0#
#377
1#
b1100 %
b0110 &
#378
0#
#379
1#
b1101 %
b0111 &
#380
0#
#381
1#
b1110 %
b1000 &
#382
0#
#383
1#
b1111 %
b1001 &
#384
0#
#385
1#
b1100 $
b0000 %
b1010 &
#386
0#
#387
1#
b0001 %
b1100 &
0'
#388
0#
#389
1#
b0010 %
b1101 &
#390
0#
#391
1#
b0011 %
b1110 &
#392
0#
#393
1#
b0100 %
b1111 &
#394
0#
#395
1#
b0101 %
b0000 &
1'
#396
0#
#397
1#
b0110 %
b0001 &
#398
0#
#399
1#
b0111 %
b0010 &
#400
0#
#401
1#
b1000 %
b0011 &
#402
0#
#403
1#
b1001 %
b0100 &
#404
0#
#405
1#
b1010 %
b0101 &
#406
0#
#407
1#
b1011 %
b0110 &
#408
0#
#409
1#
b1100 %
b0111 &
#410
0#
#411
1#
b1101 %
b1000 &
#412
0#
#413
1#
b1110 %
b1001 &
#414
0#
#415
1#
b1111 %
b1010 &
#416
0#
#417
1#
b1101 $
b0000 %
b1011 &
#418
0#
#419
1#
b0001 %
b1101 &
0'
#420
0#
#421
1#
b0010 %
b1110 &
#422
0#
#423
1#
b0011 %
b1111 &
#424
0#
#425
1#
b0100 %
b0000 &
1'
#426
0#
#427
1#
b0101 %
b0001 &
#428
0#
#429
1#
b0110 %
b0010 &
#430
0#
#431
1#
b0111 %
b0011 &
#432
0#
#433
1#
b1000 %
b0100 &
#434
0#
#435
1#
b1001 %
b0101 &
#436
0#
#437
1#
b1010 %
b0110 &
#438
0#
#439
1#
b1011 %
b0111 &
#440
0#
#441
1#
b1100 %
b1000 &
#442
0#
#443
1#
b1101 %
b1001 &
#444
0#
#445
1#
b1110 %
b1010 &
#446
0#
#447
1#
b1111 %
b1011 &
#448
0#
#449
1#
b1110 $
b0000 %
b1100 &
#450
0#
#451
1#
b0001 %
b1110 &
0'
#452
0#
#453
1#
b0010 %
b1111 &
#454
0#
#455
1#
b0011 %
b0000 &
1'
#456
0#
#457
1#
b0100 %
b0001 &
#458
0#
#459
1#
b0101 %
b0010 &
#460
0#
#461
1#
b0110 %
b0011 &
#462
0#
#463
1#
b0111 %
b0100 &
#464
0#
#465
1#
b1000 %
b0101 &
#466
0#
#467
1#
b1001 %
b0110 &
#468
0#
#469
1#
b1010 %
b0111 &
#470
0#
#471
1#
b1011 %
b1000 &
#472
0#
#473
1#
b1100 %
b1001 &
#474
0#
#475
1#
b1101 %
b1010 &
#476
0#
#477
1#
b1110 %
b1011 &
#478
0#
#479
1#
b1111 %
b1100 &
#480
0#
#481
1#
b1111 $
b0000 %
b1101 &
#482
0#
#483
1#
b0001 %
b1111 &
0'
#484
0#
#485
1#
b0010 %
b0000 &
1'
#486
0#
#487
1#
b0011 %
b0001 &
#488
0#
#489
1#
b0100 %
b0010 &
#490
0#
#491
1#
b0101 %
b0011 &
#492
0#
#493
1#
b0110 %
b0100 &
#494
0#
#495
1#
b0111 %
b0101 &
#496
0#
#497
1#
b1000 %
b0110 &
#498
0#
#499
1#
b1001 %
b0111 &
#500
0#
#501
1#
b1010 %
b1000 &
#502
0#
#503
1#
b1011 %
b1001 &
#504
0#
#505
1#
b1100 %
b1010 &
#506
0#
#507
1#
b1101 %
b1011 &
#508
0#
#509
1#
b1110 %
b1100 &
#510
0#
#511
1#
b1111 %
b1101 &
