Lab2/Tutorial/top.v
module elevator (
  input clk,
  input in_signal,
  output out_red,
  output out_green
);
  reg state;

  initial begin
    state = 0;
  end

  assign out_red = ~state;
  assign out_green = state;

  always @(posedge clk) begin
    if (in_signal) begin
      state <= 1;
    end else begin
      state <= 0;
    end
  end
endmodule

Lab2/Tutorial/top.vcd
$version Generated by VerilatedVcd $end
$date Tue Mar 21 18:38:13 2023
 $end
$timescale   1ps $end

 $scope module TOP $end
  $var wire  1 # clk $end
  $var wire  1 $ in_signal $end
  $var wire  1 & out_green $end
  $var wire  1 % out_red $end
  $scope module elevator $end
   $var wire  1 # clk $end
   $var wire  1 $ in_signal $end
   $var wire  1 & out_green $end
   $var wire  1 % out_red $end
   $var wire  1 ' state $end
  $upscope $end
 $upscope $end
$enddefinitions $end


#0
0#
0$
1%
0&
0'
#1
1#
#2
0#
#3
1#
#4
0#
#5
1#
#6
0#
#7
1#
1$
#8
0#
#9
1#
0%
1&
1'
#10
0#
#11
1#
0$
#12
0#
#13
1#
1%
0&
0'
#14
0#
#15
1#
1$
#16
0#
#17
1#
0$
0%
1&
1'
#18
0#
#19
1#
1$
1%
0&
0'
#20
0#
#21
1#
0%
1&
1'
#22
0#
#23
1#
0$
#24
0#
#25
1#
1$
1%
0&
0'
#26
0#
#27
1#
0%
1&
1'
#28
0#
#29
1#
0$
#30
0#
#31
1#
1%
0&
0'
#32
0#
#33
1#
#34
0#
#35
1#
#36
0#
#37
1#
#38
0#
#39
1#
#40
0#
#41
1#
1$
#42
0#
#43
1#
0%
1&
1'
#44
0#
#45
1#
0$
#46
0#
#47
1#
1$
1%
0&
0'
#48
0#
#49
1#
0%
1&
1'
#50
0#
#51
1#
#52
0#
#53
1#
#54
0#
#55
1#
#56
0#
#57
1#
0$
#58
0#
#59
1#
1$
1%
0&
0'
#60
0#
#61
1#
0$
0%
1&
1'
#62
0#
#63
1#
1$
1%
0&
0'
#64
0#
#65
1#
0%
1&
1'
#66
0#
#67
1#
0$
#68
0#
#69
1#
1%
0&
0'
#70
0#
#71
1#
#72
0#
#73
1#
#74
0#
#75
1#
#76
0#
#77
1#
1$
#78
0#
#79
1#
0%
1&
1'
#80
0#
#81
1#
0$
#82
0#
#83
1#
1$
1%
0&
0'
#84
0#
#85
1#
0%
1&
1'
#86
0#
#87
1#
#88
0#
#89
1#
0$
#90
0#
#91
1#
1$
1%
0&
0'
#92
0#
#93
1#
0%
1&
1'
#94
0#
#95
1#
#96
0#
#97
1#
#98
0#
#99
1#
0$
#100
0#
#101
1#
1$
1%
0&
0'
#102
0#
#103
1#
0$
0%
1&
1'
#104
0#
#105
1#
1$
1%
0&
0'
#106
0#
#107
1#
0$
0%
1&
1'
#108
0#
#109
1#
1$
1%
0&
0'
#110
0#
#111
1#
0$
0%
1&
1'
#112
0#
#113
1#
1$
1%
0&
0'
#114
0#
#115
1#
0%
1&
1'
#116
0#
#117
1#
#118
0#
#119
1#
#120
0#
#121
1#
0$
#122
0#
#123
1#
1$
1%
0&
0'
#124
0#
#125
1#
0%
1&
1'
#126
0#
#127
1#
#128
0#
#129
1#
0$
#130
0#
#131
1#
1$
1%
0&
0'
#132
0#
#133
1#
0%
1&
1'
#134
0#
#135
1#
0$
#136
0#
#137
1#
1%
0&
0'
#138
0#
#139
1#
#140
0#
#141
1#
1$
#142
0#
#143
1#
0$
0%
1&
1'
#144
0#
#145
1#
1$
1%
0&
0'
#146
0#
#147
1#
0$
0%
1&
1'
#148
0#
#149
1#
1$
1%
0&
0'
#150
0#
#151
1#
0$
0%
1&
1'
#152
0#
#153
1#
1$
1%
0&
0'
#154
0#
#155
1#
0$
0%
1&
1'
#156
0#
#157
1#
1$
1%
0&
0'
#158
0#
#159
1#
0%
1&
1'
#160
0#
#161
1#
0$
#162
0#
#163
1#
1%
0&
0'
#164
0#
#165
1#
1$
#166
0#
#167
1#
0%
1&
1'
#168
0#
#169
1#
0$
#170
0#
#171
1#
1$
1%
0&
0'
#172
0#
#173
1#
0%
1&
1'
#174
0#
#175
1#
#176
0#
#177
1#
0$
#178
0#
#179
1#
1%
0&
0'
#180
0#
#181
1#
1$
#182
0#
#183
1#
0$
0%
1&
1'
#184
0#
#185
1#
1%
0&
0'
#186
0#
#187
1#
#188
0#
#189
1#
1$
#190
0#
#191
1#
0$
0%
1&
1'
#192
0#
#193
1#
1$
1%
0&
0'
#194
0#
#195
1#
0$
0%
1&
1'
#196
0#
#197
1#
1%
0&
0'
#198
0#
#199
1#
1$
#200
0#
#201
1#
0$
0%
1&
1'
#202
0#
#203
1#
1%
0&
0'
#204
0#
#205
1#
1$
#206
0#
#207
1#
0$
0%
1&
1'
#208
0#
#209
1#
1%
0&
0'
#210
0#
#211
1#
#212
0#
#213
1#
#214
0#
#215
1#
#216
0#
#217
1#
1$
#218
0#
#219
1#
0%
1&
1'
#220
0#
#221
1#
#222
0#
#223
1#
#224
0#
#225
1#
#226
0#
#227
1#
0$
#228
0#
#229
1#
1$
1%
0&
0'
#230
0#
#231
1#
0$
0%
1&
1'
#232
0#
#233
1#
1$
1%
0&
0'
#234
0#
#235
1#
0$
0%
1&
1'
#236
0#
#237
1#
1$
1%
0&
0'
#238
0#
#239
1#
0%
1&
1'
#240
0#
#241
1#
#242
0#
#243
1#
0$
#244
0#
#245
1#
1$
1%
0&
0'
#246
0#
#247
1#
0%
1&
1'
#248
0#
#249
1#
0$
#250
0#
#251
1#
1%
0&
0'
#252
0#
#253
1#
1$
#254
0#
#255
1#
0$
0%
1&
1'
#256
0#
#257
1#
1%
0&
0'
