Lab1/adder/top.v
module top #(
    parameter BITWIDTH = 4
)(
	input [BITWIDTH-1:0] in_a,	// 4-bits Input1
	input [BITWIDTH-1:0] in_b,	// 4-bits Input1
	output [BITWIDTH-1:0] out_d,// 4-bits Output
	output out_ovf				// Output for overflow
);
    assign {out_ovf, out_d} = in_a + in_b;
endmodule

Lab1/adder/top.vcd
$version Generated by VerilatedVcd $end
$date Tue Mar 21 18:30:21 2023
 $end
$timescale   1ps $end

 $scope module TOP $end
  $var wire  4 # in_a [3:0] $end
  $var wire  4 $ in_b [3:0] $end
  $var wire  4 % out_d [3:0] $end
  $var wire  1 & out_ovf $end
  $scope module top $end
   $var wire 32 ' BITWIDTH [31:0] $end
   $var wire  4 # in_a [3:0] $end
   $var wire  4 $ in_b [3:0] $end
   $var wire  4 % out_d [3:0] $end
   $var wire  1 & out_ovf $end
  $upscope $end
 $upscope $end
$enddefinitions $end


#0
b0000 #
b0000 $
b0000 %
0&
b00000000000000000000000000000100 '
#1
b0001 $
b0001 %
#2
b0010 $
b0010 %
#3
b0011 $
b0011 %
#4
b0100 $
b0100 %
#5
b0101 $
b0101 %
#6
b0110 $
b0110 %
#7
b0111 $
b0111 %
#8
b1000 $
b1000 %
#9
b1001 $
b1001 %
#10
b1010 $
b1010 %
#11
b1011 $
b1011 %
#12
b1100 $
b1100 %
#13
b1101 $
b1101 %
#14
b1110 $
b1110 %
#15
b1111 $
b1111 %
#16
b0001 #
b0000 $
b0001 %
#17
b0001 $
b0010 %
#18
b0010 $
b0011 %
#19
b0011 $
b0100 %
#20
b0100 $
b0101 %
#21
b0101 $
b0110 %
#22
b0110 $
b0111 %
#23
b0111 $
b1000 %
#24
b1000 $
b1001 %
#25
b1001 $
b1010 %
#26
b1010 $
b1011 %
#27
b1011 $
b1100 %
#28
b1100 $
b1101 %
#29
b1101 $
b1110 %
#30
b1110 $
b1111 %
#31
b1111 $
b0000 %
1&
#32
b0010 #
b0000 $
b0010 %
0&
#33
b0001 $
b0011 %
#34
b0010 $
b0100 %
#35
b0011 $
b0101 %
#36
b0100 $
b0110 %
#37
b0101 $
b0111 %
#38
b0110 $
b1000 %
#39
b0111 $
b1001 %
#40
b1000 $
b1010 %
#41
b1001 $
b1011 %
#42
b1010 $
b1100 %
#43
b1011 $
b1101 %
#44
b1100 $
b1110 %
#45
b1101 $
b1111 %
#46
b1110 $
b0000 %
1&
#47
b1111 $
b0001 %
#48
b0011 #
b0000 $
b0011 %
0&
#49
b0001 $
b0100 %
#50
b0010 $
b0101 %
#51
b0011 $
b0110 %
#52
b0100 $
b0111 %
#53
b0101 $
b1000 %
#54
b0110 $
b1001 %
#55
b0111 $
b1010 %
#56
b1000 $
b1011 %
#57
b1001 $
b1100 %
#58
b1010 $
b1101 %
#59
b1011 $
b1110 %
#60
b1100 $
b1111 %
#61
b1101 $
b0000 %
1&
#62
b1110 $
b0001 %
#63
b1111 $
b0010 %
#64
b0100 #
b0000 $
b0100 %
0&
#65
b0001 $
b0101 %
#66
b0010 $
b0110 %
#67
b0011 $
b0111 %
#68
b0100 $
b1000 %
#69
b0101 $
b1001 %
#70
b0110 $
b1010 %
#71
b0111 $
b1011 %
#72
b1000 $
b1100 %
#73
b1001 $
b1101 %
#74
b1010 $
b1110 %
#75
b1011 $
b1111 %
#76
b1100 $
b0000 %
1&
#77
b1101 $
b0001 %
#78
b1110 $
b0010 %
#79
b1111 $
b0011 %
#80
b0101 #
b0000 $
b0101 %
0&
#81
b0001 $
b0110 %
#82
b0010 $
b0111 %
#83
b0011 $
b1000 %
#84
b0100 $
b1001 %
#85
b0101 $
b1010 %
#86
b0110 $
b1011 %
#87
b0111 $
b1100 %
#88
b1000 $
b1101 %
#89
b1001 $
b1110 %
#90
b1010 $
b1111 %
#91
b1011 $
b0000 %
1&
#92
b1100 $
b0001 %
#93
b1101 $
b0010 %
#94
b1110 $
b0011 %
#95
b1111 $
b0100 %
#96
b0110 #
b0000 $
b0110 %
0&
#97
b0001 $
b0111 %
#98
b0010 $
b1000 %
#99
b0011 $
b1001 %
#100
b0100 $
b1010 %
#101
b0101 $
b1011 %
#102
b0110 $
b1100 %
#103
b0111 $
b1101 %
#104
b1000 $
b1110 %
#105
b1001 $
b1111 %
#106
b1010 $
b0000 %
1&
#107
b1011 $
b0001 %
#108
b1100 $
b0010 %
#109
b1101 $
b0011 %
#110
b1110 $
b0100 %
#111
b1111 $
b0101 %
#112
b0111 #
b0000 $
b0111 %
0&
#113
b0001 $
b1000 %
#114
b0010 $
b1001 %
#115
b0011 $
b1010 %
#116
b0100 $
b1011 %
#117
b0101 $
b1100 %
#118
b0110 $
b1101 %
#119
b0111 $
b1110 %
#120
b1000 $
b1111 %
#121
b1001 $
b0000 %
1&
#122
b1010 $
b0001 %
#123
b1011 $
b0010 %
#124
b1100 $
b0011 %
#125
b1101 $
b0100 %
#126
b1110 $
b0101 %
#127
b1111 $
b0110 %
#128
b1000 #
b0000 $
b1000 %
0&
#129
b0001 $
b1001 %
#130
b0010 $
b1010 %
#131
b0011 $
b1011 %
#132
b0100 $
b1100 %
#133
b0101 $
b1101 %
#134
b0110 $
b1110 %
#135
b0111 $
b1111 %
#136
b1000 $
b0000 %
1&
#137
b1001 $
b0001 %
#138
b1010 $
b0010 %
#139
b1011 $
b0011 %
#140
b1100 $
b0100 %
#141
b1101 $
b0101 %
#142
b1110 $
b0110 %
#143
b1111 $
b0111 %
#144
b1001 #
b0000 $
b1001 %
0&
#145
b0001 $
b1010 %
#146
b0010 $
b1011 %
#147
b0011 $
b1100 %
#148
b0100 $
b1101 %
#149
b0101 $
b1110 %
#150
b0110 $
b1111 %
#151
b0111 $
b0000 %
1&
#152
b1000 $
b0001 %
#153
b1001 $
b0010 %
#154
b1010 $
b0011 %
#155
b1011 $
b0100 %
#156
b1100 $
b0101 %
#157
b1101 $
b0110 %
#158
b1110 $
b0111 %
#159
b1111 $
b1000 %
#160
b1010 #
b0000 $
b1010 %
0&
#161
b0001 $
b1011 %
#162
b0010 $
b1100 %
#163
b0011 $
b1101 %
#164
b0100 $
b1110 %
#165
b0101 $
b1111 %
#166
b0110 $
b0000 %
1&
#167
b0111 $
b0001 %
#168
b1000 $
b0010 %
#169
b1001 $
b0011 %
#170
b1010 $
b0100 %
#171
b1011 $
b0101 %
#172
b1100 $
b0110 %
#173
b1101 $
b0111 %
#174
b1110 $
b1000 %
#175
b1111 $
b1001 %
#176
b1011 #
b0000 $
b1011 %
0&
#177
b0001 $
b1100 %
#178
b0010 $
b1101 %
#179
b0011 $
b1110 %
#180
b0100 $
b1111 %
#181
b0101 $
b0000 %
1&
#182
b0110 $
b0001 %
#183
b0111 $
b0010 %
#184
b1000 $
b0011 %
#185
b1001 $
b0100 %
#186
b1010 $
b0101 %
#187
b1011 $
b0110 %
#188
b1100 $
b0111 %
#189
b1101 $
b1000 %
#190
b1110 $
b1001 %
#191
b1111 $
b1010 %
#192
b1100 #
b0000 $
b1100 %
0&
#193
b0001 $
b1101 %
#194
b0010 $
b1110 %
#195
b0011 $
b1111 %
#196
b0100 $
b0000 %
1&
#197
b0101 $
b0001 %
#198
b0110 $
b0010 %
#199
b0111 $
b0011 %
#200
b1000 $
b0100 %
#201
b1001 $
b0101 %
#202
b1010 $
b0110 %
#203
b1011 $
b0111 %
#204
b1100 $
b1000 %
#205
b1101 $
b1001 %
#206
b1110 $
b1010 %
#207
b1111 $
b1011 %
#208
b1101 #
b0000 $
b1101 %
0&
#209
b0001 $
b1110 %
#210
b0010 $
b1111 %
#211
b0011 $
b0000 %
1&
#212
b0100 $
b0001 %
#213
b0101 $
b0010 %
#214
b0110 $
b0011 %
#215
b0111 $
b0100 %
#216
b1000 $
b0101 %
#217
b1001 $
b0110 %
#218
b1010 $
b0111 %
#219
b1011 $
b1000 %
#220
b1100 $
b1001 %
#221
b1101 $
b1010 %
#222
b1110 $
b1011 %
#223
b1111 $
b1100 %
#224
b1110 #
b0000 $
b1110 %
0&
#225
b0001 $
b1111 %
#226
b0010 $
b0000 %
1&
#227
b0011 $
b0001 %
#228
b0100 $
b0010 %
#229
b0101 $
b0011 %
#230
b0110 $
b0100 %
#231
b0111 $
b0101 %
#232
b1000 $
b0110 %
#233
b1001 $
b0111 %
#234
b1010 $
b1000 %
#235
b1011 $
b1001 %
#236
b1100 $
b1010 %
#237
b1101 $
b1011 %
#238
b1110 $
b1100 %
#239
b1111 $
b1101 %
#240
b1111 #
b0000 $
b1111 %
0&
#241
b0001 $
b0000 %
1&
#242
b0010 $
b0001 %
#243
b0011 $
b0010 %
#244
b0100 $
b0011 %
#245
b0101 $
b0100 %
#246
b0110 $
b0101 %
#247
b0111 $
b0110 %
#248
b1000 $
b0111 %
#249
b1001 $
b1000 %
#250
b1010 $
b1001 %
#251
b1011 $
b1010 %
#252
b1100 $
b1011 %
#253
b1101 $
b1100 %
#254
b1110 $
b1101 %
#255
b1111 $
b1110 %
