Lab2/Practice/my_mac.v
module my_mac #(
	parameter BITWIDTH = 4
)
(
  input [BITWIDTH-1:0] in_a,
  input in_a_valid,
  input [BITWIDTH-1:0] in_b,
  input in_b_valid,
  input clk,
  input in_rst,
  output reg [2*BITWIDTH-1:0] out_d,
  output reg out_ovf,
  output reg out_d_valid
);

  wire [2*BITWIDTH:0] multi;
  assign multi = in_a * in_b + out_d;

  always @(posedge clk) begin
    if(in_rst) begin
      out_d <= 0;
      out_d_valid <= 0;
      out_ovf <= 0;
    end
    else begin
      if (in_a_valid & in_b_valid) begin
        out_d_valid <= 1;

        out_d <= multi[2*BITWIDTH-1:0];

        if(!out_ovf & multi[2*BITWIDTH]) begin
          out_ovf <= 1;
        end
      end
    end
  end

endmodule

Lab2/Practice/top.v
module my_pe #(
	parameter BITWIDTH = 4,
  parameter FAN_IN_BITS = 3,
  parameter INIT = 0,
  parameter EXEC = 1
)
(
  input [BITWIDTH-1:0] in_a,
  input [BITWIDTH-1:0] in_b,
  output [2*BITWIDTH-1:0] out_d,
  output reg out_d_valid,
  output out_ovf,
  input clk,
  input in_init
);
    // state == 0 --> INIT
    // state == 1 --> EXEC
    reg state;
    reg [FAN_IN_BITS-1:0] counter;

    // TODO
    my_mac my_mac(
      .in_a(in_a),
      .in_a_valid(state),
      .in_b(in_b),
      .in_b_valid(state),
      .clk(clk),
      .in_rst(in_init),
      .out_d(out_d),
      .out_d_valid(),
      .out_ovf(out_ovf)
    );

    initial begin
      state = 0;
    end

    always @(posedge clk) begin
      // if INIT --> wait for in_init signal
      //             if in_init, state changes to EXEC
      case(state)
        INIT: if(in_init == 1) begin 
          state <= EXEC; out_d_valid = 0;
        end
        EXEC: if(counter == 2**FAN_IN_BITS - 1) begin
          state <= INIT; out_d_valid = 1;
        end
      endcase

      case(state)
        INIT: begin
        end
        EXEC: begin

          if(counter == 2**FAN_IN_BITS - 1) counter = 0;
          else counter = counter + 1;
          
        end
      endcase
  
    end

endmodule

Lab2/Practice/top.vcd
$version Generated by VerilatedVcd $end
$date Wed Mar 22 09:27:52 2023
 $end
$timescale   1ps $end

 $scope module TOP $end
  $var wire  1 + clk $end
  $var wire  4 & in_a [3:0] $end
  $var wire  4 ' in_b [3:0] $end
  $var wire  1 , in_init $end
  $var wire  8 ( out_d [7:0] $end
  $var wire  1 ) out_d_valid $end
  $var wire  1 * out_ovf $end
  $scope module my_pe $end
   $var wire 32 . BITWIDTH [31:0] $end
   $var wire 32 1 EXEC [31:0] $end
   $var wire 32 / FAN_IN_BITS [31:0] $end
   $var wire 32 0 INIT [31:0] $end
   $var wire  1 + clk $end
   $var wire  3 $ counter [2:0] $end
   $var wire  4 & in_a [3:0] $end
   $var wire  4 ' in_b [3:0] $end
   $var wire  1 , in_init $end
   $var wire  8 ( out_d [7:0] $end
   $var wire  1 ) out_d_valid $end
   $var wire  1 * out_ovf $end
   $var wire  1 # state $end
   $scope module my_mac $end
    $var wire 32 . BITWIDTH [31:0] $end
    $var wire  1 + clk $end
    $var wire  4 & in_a [3:0] $end
    $var wire  1 # in_a_valid $end
    $var wire  4 ' in_b [3:0] $end
    $var wire  1 # in_b_valid $end
    $var wire  1 , in_rst $end
    $var wire  9 - multi [8:0] $end
    $var wire  8 ( out_d [7:0] $end
    $var wire  1 % out_d_valid $end
    $var wire  1 * out_ovf $end
   $upscope $end
  $upscope $end
 $upscope $end
$enddefinitions $end


#0
0#
b000 $
0%
b0000 &
b0000 '
b00000000 (
0)
0*
0+
0,
b000000000 -
b00000000000000000000000000000100 .
b00000000000000000000000000000011 /
b00000000000000000000000000000000 0
b00000000000000000000000000000001 1
#1
b0111 &
b0110 '
1+
#2
0+
b000101010 -
#3
b1001 &
b0011 '
1+
#4
0+
b000011011 -
#5
b0001 &
b1111 '
1+
#6
0+
b000001111 -
#7
b1010 &
b1100 '
1+
#8
0+
b001111000 -
#9
b1001 &
b1101 '
1+
#10
0+
b001110101 -
#11
b1010 &
b1011 '
1+
#12
0+
b001101110 -
#13
b0010 &
1+
#14
0+
b000010110 -
#15
b0011 &
b0110 '
1+
#16
0+
b000010010 -
#17
b1100 &
b0010 '
1+
#18
0+
b000011000 -
#19
b0100 &
b1000 '
1+
#20
0+
b000100000 -
#21
b1011 &
1+
#22
0+
b001011000 -
#23
b0111 &
b1101 '
1+
#24
0+
b001011011 -
#25
b0110 &
b1010 '
1+
#26
0+
b000111100 -
#27
b1110 &
b0011 '
1+
#28
0+
b000101010 -
#29
b0011 &
b1111 '
1+
#30
0+
b000101101 -
#31
b1001 &
b1010 '
1+
1,
#32
0+
b001011010 -
#33
1#
b0110 &
b0010 '
1+
0,
#34
0+
b000001100 -
#35
b001 $
1%
b1101 &
b0111 '
b00001100 (
1+
b000011000 -
#36
0+
b001100111 -
#37
b010 $
b0001 &
b1000 '
b01100111 (
1+
b011000010 -
#38
0+
b001101111 -
#39
b011 $
b0011 &
b1010 '
b01101111 (
1+
b001110111 -
#40
0+
b010001101 -
#41
b100 $
b0101 &
b1101 '
b10001101 (
1+
b010101011 -
#42
0+
b011001110 -
#43
b101 $
b0111 '
b11001110 (
1+
b100001111 -
#44
0+
b011110001 -
#45
b110 $
b1000 &
b1001 '
b11110001 (
1+
b100010100 -
#46
0+
b100111001 -
#47
b111 $
b1110 &
b0100 '
b00111001 (
1*
1+
b010000001 -
#48
0+
b001110001 -
#49
0#
b000 $
b1011 &
b0010 '
b01110001 (
1)
1+
b010101001 -
#50
0+
b010000111 -
#51
b1101 &
b0110 '
1+
#52
0+
b010111111 -
#53
b1011 &
b0100 '
1+
#54
0+
b010011101 -
#55
b0100 &
b0001 '
1+
#56
0+
b001110101 -
#57
b1110 &
b0010 '
1+
#58
0+
b010001101 -
#59
b0100 &
b0001 '
1+
#60
0+
b001110101 -
#61
b0001 &
b1101 '
1+
#62
0+
b001111110 -
#63
b1100 &
b0111 '
1+
1,
#64
0+
b011000101 -
#65
1#
0%
b0000 &
b1001 '
b00000000 (
0)
0*
1+
0,
b001010100 -
#66
0+
b000000000 -
#67
b001 $
1%
b1110 &
b0001 '
1+
#68
0+
b000001110 -
#69
b010 $
b0001 &
b00001110 (
1+
b000011100 -
#70
0+
b000001111 -
#71
b011 $
b1100 &
b0111 '
b00001111 (
1+
b000010000 -
#72
0+
b001100011 -
#73
b100 $
b1110 &
b0001 '
b01100011 (
1+
b010110111 -
#74
0+
b001110001 -
#75
b101 $
b0111 '
b01110001 (
1+
b001111111 -
#76
0+
b011010011 -
#77
b110 $
b1010 &
b1100 '
b11010011 (
1+
b100110101 -
#78
0+
b101001011 -
#79
b111 $
b1011 &
b0110 '
b01001011 (
1*
1+
b011000011 -
#80
0+
b010001101 -
#81
0#
b000 $
b1111 &
b1000 '
b10001101 (
1)
1+
b011001111 -
#82
0+
b100000101 -
#83
b1100 &
b1010 '
1+
#84
0+
#85
b0000 '
1+
#86
0+
b010001101 -
#87
b1011 &
b1011 '
1+
#88
0+
b100000110 -
#89
b0010 &
b1111 '
1+
#90
0+
b010101011 -
#91
b1100 &
b0100 '
1+
#92
0+
b010111101 -
#93
b1000 '
1+
#94
0+
b011101101 -
#95
b1011 &
b1100 '
1+
1,
#96
0+
b100010001 -
#97
1#
0%
b0010 &
b1010 '
b00000000 (
0)
0*
1+
0,
b010000100 -
#98
0+
b000010100 -
#99
b001 $
1%
b1110 &
b0011 '
b00010100 (
1+
b000101000 -
#100
0+
b000111110 -
#101
b010 $
b1011 &
b1010 '
b00111110 (
1+
b001101000 -
#102
0+
b010101100 -
#103
b011 $
b1010 &
b10101100 (
1+
b100011010 -
#104
0+
b100010000 -
#105
b100 $
b1011 &
b1001 '
b00010000 (
1*
1+
b001110100 -
#106
0+
b001110011 -
#107
b101 $
b0001 &
b0110 '
b01110011 (
1+
b011010110 -
#108
0+
b001111001 -
#109
b110 $
b0101 &
b1100 '
b01111001 (
1+
b001111111 -
#110
0+
b010110101 -
#111
b111 $
b1100 &
b0100 '
b10110101 (
1+
b011110001 -
#112
0+
b011100101 -
#113
0#
b000 $
b0101 &
b1000 '
b11100101 (
1)
1+
b100010101 -
#114
0+
b100001101 -
#115
b1110 &
b0001 '
1+
#116
0+
b011110011 -
#117
b1001 &
b1001 '
1+
#118
0+
b100110110 -
#119
b1100 &
b1011 '
1+
#120
0+
b101101001 -
#121
b1000 &
b1001 '
1+
#122
0+
b100101101 -
#123
b1111 &
b0101 '
1+
#124
0+
b100110000 -
#125
b0001 &
b1011 '
1+
#126
0+
b011110000 -
#127
b0011 '
1+
1,
#128
0+
b011101000 -
#129
1#
0%
b0101 &
b1111 '
b00000000 (
0)
0*
1+
0,
b000000011 -
#130
0+
b001001011 -
#131
b001 $
1%
b0111 &
b0000 '
b01001011 (
1+
b010010110 -
#132
0+
b001001011 -
#133
b010 $
b1001 &
b0001 '
1+
#134
0+
b001010100 -
#135
b011 $
b1010 &
b0101 '
b01010100 (
1+
b001011101 -
#136
0+
b010000110 -
#137
b100 $
b1011 '
b10000110 (
1+
b010111000 -
#138
0+
b011110100 -
#139
b101 $
b1011 &
b0000 '
b11110100 (
1+
b101100010 -
#140
0+
b011110100 -
#141
b110 $
b1000 &
b0111 '
1+
#142
0+
b100101100 -
#143
b111 $
b0100 &
b1101 '
b00101100 (
1*
1+
b001100100 -
#144
0+
b001100000 -
#145
0#
b000 $
b1111 &
b0011 '
b01100000 (
1)
1+
b010010100 -
#146
0+
b010001101 -
#147
b1110 &
b1000 '
1+
#148
0+
b011010000 -
#149
b1100 &
b1011 '
1+
#150
0+
b011100100 -
#151
b0100 &
b0101 '
1+
#152
0+
b001110100 -
#153
b0011 '
1+
#154
0+
b001101100 -
#155
b1010 &
b0101 '
1+
#156
0+
b010010010 -
#157
b1110 &
b1011 '
1+
#158
0+
b011111010 -
#159
b1001 &
b0011 '
1+
1,
#160
0+
b001111011 -
#161
1#
0%
b1011 &
b0000 '
b00000000 (
0)
0*
1+
0,
b000011011 -
#162
0+
b000000000 -
#163
b001 $
1%
b0100 &
b0100 '
1+
#164
0+
b000010000 -
#165
b010 $
b0001 &
b1110 '
b00010000 (
1+
b000100000 -
#166
0+
b000011110 -
#167
b011 $
b1001 &
b1100 '
b00011110 (
1+
b000101100 -
#168
0+
b010001010 -
#169
b100 $
b1010 &
b0100 '
b10001010 (
1+
b011110110 -
#170
0+
b010110010 -
#171
b101 $
b1100 &
b0010 '
b10110010 (
1+
b011011010 -
#172
0+
b011001010 -
#173
b110 $
b1011 &
b0000 '
b11001010 (
1+
b011100010 -
#174
0+
b011001010 -
#175
b111 $
b1111 &
b1011 '
1+
#176
0+
b101101111 -
#177
0#
b000 $
b0011 &
b1101 '
b01101111 (
1)
1*
1+
b100010100 -
#178
0+
b010010110 -
#179
b0000 '
1+
#180
0+
b001101111 -
#181
b1000 &
b0111 '
1+
#182
0+
b010100111 -
#183
b0101 &
b1100 '
1+
#184
0+
b010101011 -
#185
b1011 &
b1111 '
1+
#186
0+
b100010100 -
#187
b0010 &
b1001 '
1+
#188
0+
b010000001 -
#189
b1010 &
b1011 '
1+
#190
0+
b011011101 -
#191
b1101 &
b0101 '
1+
1,
#192
0+
b010110000 -
#193
1#
0%
b1011 &
b0001 '
b00000000 (
0)
0*
1+
0,
b001000001 -
#194
0+
b000001011 -
#195
b001 $
1%
b1010 &
b1100 '
b00001011 (
1+
b000010110 -
#196
0+
b010000011 -
#197
b010 $
b1111 &
b0011 '
b10000011 (
1+
b011111011 -
#198
0+
b010110000 -
#199
b011 $
b1000 &
b1001 '
b10110000 (
1+
b011011101 -
#200
0+
b011111000 -
#201
b100 $
b0100 '
b11111000 (
1+
b101000000 -
#202
0+
b100011000 -
#203
b101 $
b1011 &
b0011 '
b00011000 (
1*
1+
b000111000 -
#204
0+
b000111001 -
#205
b110 $
b0101 &
b1010 '
b00111001 (
1+
b001011010 -
#206
0+
b001101011 -
#207
b111 $
b1110 &
b1000 '
b01101011 (
1+
b010011101 -
#208
0+
b011011011 -
#209
0#
b000 $
b1000 &
b0010 '
b11011011 (
1)
1+
b101001011 -
#210
0+
b011101011 -
#211
b0000 '
1+
#212
0+
b011011011 -
#213
b1001 &
b1101 '
1+
#214
0+
b101010000 -
#215
b1101 &
b0100 '
1+
#216
0+
b100001111 -
#217
b1100 &
b1111 '
1+
#218
0+
b110001111 -
#219
b1110 &
b0111 '
1+
#220
0+
b100111101 -
#221
b1010 &
b1011 '
1+
#222
0+
b101001001 -
#223
b1100 &
b0101 '
1+
1,
#224
0+
b100010111 -
#225
1#
0%
b0110 '
b00000000 (
0)
0*
1+
0,
b000111100 -
#226
0+
b001001000 -
#227
b001 $
1%
b0001 &
b1011 '
b01001000 (
1+
b010010000 -
#228
0+
b001010011 -
#229
b010 $
b1010 &
b1010 '
b01010011 (
1+
b001011110 -
#230
0+
b010110111 -
#231
b011 $
b0101 &
b0010 '
b10110111 (
1+
b100011011 -
#232
0+
b011000001 -
#233
b100 $
b1110 &
b0000 '
b11000001 (
1+
b011001011 -
#234
0+
b011000001 -
#235
b101 $
b0101 &
b0011 '
1+
#236
0+
b011010000 -
#237
b110 $
b1011 &
b0100 '
b11010000 (
1+
b011011111 -
#238
0+
b011111100 -
#239
b111 $
b1100 &
b0011 '
b11111100 (
1+
b100101000 -
#240
0+
b100100000 -
#241
0#
b000 $
b0110 &
b0100 '
b00100000 (
1)
1*
1+
b001000100 -
#242
0+
b000111000 -
#243
b0011 &
b1111 '
1+
#244
0+
b001001101 -
#245
b0010 &
b0000 '
1+
#246
0+
b000100000 -
#247
b0100 &
b1110 '
1+
#248
0+
b001011000 -
#249
b1111 &
b0010 '
1+
#250
0+
b000111110 -
#251
b0101 &
b1001 '
1+
#252
0+
b001001101 -
#253
b1101 &
b0010 '
1+
#254
0+
b000111010 -
#255
b1110 &
b1001 '
1+
1,
#256
0+
b010011110 -
#257
1#
0%
b1000 &
b0000 '
b00000000 (
0)
0*
1+
0,
b001111110 -
#258
0+
b000000000 -
#259
b001 $
1%
b0100 &
b0010 '
1+
#260
0+
b000001000 -
#261
b010 $
b1010 &
b1001 '
b00001000 (
1+
b000010000 -
#262
0+
b001100010 -
#263
b011 $
b0100 &
b1000 '
b01100010 (
1+
b010111100 -
#264
0+
b010000010 -
#265
b100 $
b1010 &
b1010 '
b10000010 (
1+
b010100010 -
#266
0+
b011100110 -
#267
b101 $
b1100 &
b0101 '
b11100110 (
1+
b101001010 -
#268
0+
b100100010 -
#269
b110 $
b1110 &
b1000 '
b00100010 (
1*
1+
b001011110 -
#270
0+
b010010010 -
#271
b111 $
b1000 &
b0100 '
b10010010 (
1+
b100000010 -
#272
0+
b010110010 -
#273
0#
b000 $
b1100 &
b1011 '
b10110010 (
1)
1+
b011010010 -
#274
0+
b100110110 -
#275
b0011 &
b1110 '
1+
#276
0+
b011011100 -
#277
b1100 &
b0111 '
1+
#278
0+
b100000110 -
#279
b1101 &
b1011 '
1+
#280
0+
b101000001 -
#281
b1001 &
b0010 '
1+
#282
0+
b011000100 -
#283
b0101 &
b0110 '
1+
#284
0+
b011010000 -
#285
b0100 &
b0011 '
1+
#286
0+
b010111110 -
#287
b1111 &
b1101 '
1+
1,
#288
0+
b101110101 -
#289
1#
0%
b0011 &
b0100 '
b00000000 (
0)
0*
1+
0,
b011000011 -
#290
0+
b000001100 -
#291
b001 $
1%
b1111 &
b1101 '
b00001100 (
1+
b000011000 -
#292
0+
b011001111 -
#293
b010 $
b1101 &
b0100 '
b11001111 (
1+
b110010010 -
#294
0+
b100000011 -
#295
b011 $
b0110 &
b0111 '
b00000011 (
1*
1+
b000110111 -
#296
0+
b000101101 -
#297
b100 $
b1110 &
b0010 '
b00101101 (
1+
b001010111 -
#298
0+
b001001001 -
#299
b101 $
b1100 &
b1100 '
b01001001 (
1+
b001100101 -
#300
0+
b011011001 -
#301
b110 $
b1010 &
b0100 '
b11011001 (
1+
b101101001 -
#302
0+
b100000001 -
#303
b111 $
b0000 &
b0110 '
b00000001 (
1+
b000101001 -
#304
0+
b000000001 -
#305
0#
b000 $
b0011 '
1)
1+
#306
0+
#307
b0101 &
b1100 '
1+
#308
0+
b000111101 -
#309
b1011 &
b0010 '
1+
#310
0+
b000010111 -
#311
b0111 &
b0100 '
1+
#312
0+
b000011101 -
#313
b0100 &
b1100 '
1+
#314
0+
b000110001 -
#315
b1011 &
b1001 '
1+
#316
0+
b001100100 -
#317
b0000 &
b1010 '
1+
#318
0+
b000000001 -
#319
b0110 &
b0011 '
1+
1,
#320
0+
b000010011 -
#321
1#
0%
b1110 &
b0101 '
b00000000 (
0)
0*
1+
0,
b000010010 -
#322
0+
b001000110 -
#323
b001 $
1%
b0001 &
b1100 '
b01000110 (
1+
b010001100 -
#324
0+
b001010010 -
#325
b010 $
b1001 &
b0111 '
b01010010 (
1+
b001011110 -
#326
0+
b010010001 -
#327
b011 $
b0011 &
b10010001 (
1+
b011010000 -
#328
0+
b010100110 -
#329
b100 $
b1001 &
b0000 '
b10100110 (
1+
b010111011 -
#330
0+
b010100110 -
#331
b101 $
b0011 &
b0011 '
1+
#332
0+
b010101111 -
#333
b110 $
b0100 &
b10101111 (
1+
b010111000 -
#334
0+
b010111011 -
#335
b111 $
b1001 &
b0100 '
b10111011 (
1+
b011000111 -
#336
0+
b011011111 -
#337
0#
b000 $
b0111 &
b1110 '
b11011111 (
1)
1+
b100000011 -
#338
0+
b101000001 -
#339
b0000 &
b0010 '
1+
#340
0+
b011011111 -
#341
b1000 '
1+
#342
0+
#343
b0110 &
b0101 '
1+
#344
0+
b011111101 -
#345
b0100 &
b0001 '
1+
#346
0+
b011100011 -
#347
b1110 &
b0100 '
1+
#348
0+
b100010111 -
#349
b1100 &
1+
#350
0+
b100001111 -
#351
b1000 &
b1010 '
1+
1,
#352
0+
b100101111 -
#353
1#
0%
b1001 &
b1001 '
b00000000 (
0)
1+
0,
b001010000 -
#354
0+
b001010001 -
#355
b001 $
1%
b0110 &
b0011 '
b01010001 (
1+
b010100010 -
#356
0+
b001100011 -
#357
b010 $
b0000 &
b1010 '
b01100011 (
1+
b001110101 -
#358
0+
b001100011 -
#359
b011 $
b1010 &
b1001 '
1+
#360
0+
b010111101 -
#361
b100 $
b1110 '
b10111101 (
1+
b100010111 -
#362
0+
b101001001 -
#363
b101 $
b1100 &
b01001001 (
1*
1+
b011010101 -
#364
0+
b011110001 -
#365
b110 $
b0001 &
b0101 '
b11110001 (
1+
b110011001 -
#366
0+
b011110110 -
#367
b111 $
b0011 &
b1000 '
b11110110 (
1+
b011111011 -
#368
0+
b100001110 -
#369
0#
b000 $
b0100 &
b0011 '
b00001110 (
1)
1+
b000100110 -
#370
0+
b000011010 -
#371
b1010 &
b0100 '
1+
#372
0+
b000110110 -
#373
b1011 &
b0001 '
1+
#374
0+
b000011001 -
#375
b1001 &
b0000 '
1+
#376
0+
b000001110 -
#377
b0010 &
b0111 '
1+
#378
0+
b000011100 -
#379
b0100 &
b1110 '
1+
#380
0+
b001000110 -
#381
b1011 &
b1100 '
1+
#382
0+
b010010010 -
#383
b1001 &
b0101 '
1+
1,
#384
0+
b000111011 -
#385
1#
0%
b0101 &
b1111 '
b00000000 (
0)
0*
1+
0,
b000101101 -
#386
0+
b001001011 -
#387
b001 $
1%
b1000 &
b0101 '
b01001011 (
1+
b010010110 -
#388
0+
b001110011 -
#389
b010 $
b1001 &
b0010 '
b01110011 (
1+
b010011011 -
#390
0+
b010000101 -
#391
b011 $
b1110 &
b0011 '
b10000101 (
1+
b010010111 -
#392
0+
b010101111 -
#393
b100 $
b0000 &
b1010 '
b10101111 (
1+
b011011001 -
#394
0+
b010101111 -
#395
b101 $
b0010 &
b0010 '
1+
#396
0+
b010110011 -
#397
b110 $
b0000 &
b0101 '
b10110011 (
1+
b010110111 -
#398
0+
b010110011 -
#399
b111 $
b1010 &
b0100 '
1+
#400
0+
b011011011 -
#401
0#
b000 $
b1000 &
b0101 '
b11011011 (
1)
1+
b100000011 -
#402
0+
#403
b0100 '
1+
#404
0+
b011111011 -
#405
b0110 &
b0010 '
1+
#406
0+
b011100111 -
#407
b0100 &
b1000 '
1+
#408
0+
b011111011 -
#409
b1001 &
1+
#410
0+
b100100011 -
#411
b0111 &
b0101 '
1+
#412
0+
b011111110 -
#413
b0101 &
b0000 '
1+
#414
0+
b011011011 -
#415
b1010 &
b1010 '
1+
1,
#416
0+
b100111111 -
#417
1#
0%
b1111 &
b0010 '
b00000000 (
0)
1+
0,
b001100100 -
#418
0+
b000011110 -
#419
b001 $
1%
b0000 &
b1001 '
b00011110 (
1+
b000111100 -
#420
0+
b000011110 -
#421
b010 $
b0100 &
b1110 '
1+
#422
0+
b001010110 -
#423
b011 $
b1100 &
b0101 '
b01010110 (
1+
b010001110 -
#424
0+
b010010010 -
#425
b100 $
b1001 &
b1110 '
b10010010 (
1+
b011001110 -
#426
0+
b100010000 -
#427
b101 $
b0111 &
b1001 '
b00010000 (
1*
1+
b010001110 -
#428
0+
b001001111 -
#429
b110 $
b0011 &
b0001 '
b01001111 (
1+
b010001110 -
#430
0+
b001010010 -
#431
b111 $
b1101 &
b1100 '
b01010010 (
1+
b001010101 -
#432
0+
b011101110 -
#433
0#
b000 $
b0110 &
b0101 '
b11101110 (
1)
1+
b110001010 -
#434
0+
b100001100 -
#435
b0000 &
b1100 '
1+
#436
0+
b011101110 -
#437
b0111 &
b0100 '
1+
#438
0+
b100001010 -
#439
b0101 &
b0001 '
1+
#440
0+
b011110011 -
#441
b1100 &
b1100 '
1+
#442
0+
b101111110 -
#443
b0110 &
b0001 '
1+
#444
0+
b011110100 -
#445
b1100 &
b0000 '
1+
#446
0+
b011101110 -
#447
b1011 '
1+
1,
#448
0+
b101110010 -
#449
1#
0%
b0010 &
b1100 '
b00000000 (
0)
0*
1+
0,
b010000100 -
#450
0+
b000011000 -
#451
b001 $
1%
b0100 &
b0110 '
b00011000 (
1+
b000110000 -
#452
0+
#453
b010 $
b1010 &
b0001 '
b00110000 (
1+
b001001000 -
#454
0+
b000111010 -
#455
b011 $
b1011 &
b0011 '
b00111010 (
1+
b001000100 -
#456
0+
b001011011 -
#457
b100 $
b1111 &
b0010 '
b01011011 (
1+
b001111100 -
#458
0+
b001111001 -
#459
b101 $
b1100 &
b0011 '
b01111001 (
1+
b010010111 -
#460
0+
b010011101 -
#461
b110 $
b0100 &
b1001 '
b10011101 (
1+
b011000001 -
#462
0+
#463
b111 $
b1111 &
b1010 '
b11000001 (
1+
b011100101 -
#464
0+
b101010111 -
#465
0#
b000 $
b1111 '
b01010111 (
1)
1*
1+
b011101101 -
#466
0+
b100111000 -
#467
b0111 &
b0110 '
1+
#468
0+
b010000001 -
#469
b0011 &
b1100 '
1+
#470
0+
b001111011 -
#471
b0111 &
b1111 '
1+
#472
0+
b011000000 -
#473
b1000 &
b1101 '
1+
#474
0+
b010111111 -
#475
b0001 &
b0100 '
1+
#476
0+
b001011011 -
#477
b1101 &
b1101 '
1+
#478
0+
b100000000 -
#479
b1111 &
b1111 '
1+
1,
#480
0+
b100111000 -
#481
1#
0%
b1001 &
b0100 '
b00000000 (
0)
0*
1+
0,
b011100001 -
#482
0+
b000100100 -
#483
b001 $
1%
b0110 &
b0011 '
b00100100 (
1+
b001001000 -
#484
0+
b000110110 -
#485
b010 $
b0101 &
b0001 '
b00110110 (
1+
b001001000 -
#486
0+
b000111011 -
#487
b011 $
b0111 &
b0100 '
b00111011 (
1+
b001000000 -
#488
0+
b001010111 -
#489
b100 $
b0100 &
b0011 '
b01010111 (
1+
b001110011 -
#490
0+
b001100011 -
#491
b101 $
b0111 &
b1000 '
b01100011 (
1+
b001101111 -
#492
0+
b010011011 -
#493
b110 $
b1101 &
b0110 '
b10011011 (
1+
b011010011 -
#494
0+
b011101001 -
#495
b111 $
b0010 &
b1100 '
b11101001 (
1+
b100110111 -
#496
0+
b100000001 -
#497
0#
b000 $
b0101 &
b1001 '
b00000001 (
1)
1*
1+
b000011001 -
#498
0+
b000101110 -
#499
b0010 &
b1000 '
1+
#500
0+
b000010001 -
#501
b0101 &
b1010 '
1+
#502
0+
b000110011 -
#503
b1000 &
b1101 '
1+
#504
0+
b001101001 -
#505
b0111 &
b1001 '
1+
#506
0+
b001000000 -
#507
b0001 &
b0101 '
1+
#508
0+
b000000110 -
#509
b0110 &
b0001 '
1+
#510
0+
b000000111 -
#511
b0100 &
b1111 '
1+
1,
#512
0+
b000111101 -
