Lab1/practice/top.v
module my_mac #(
	parameter BITWIDTH = 4
)
(
  input [BITWIDTH-1:0] in_a,
  input in_a_valid,
  input [BITWIDTH-1:0] in_b,
  input in_b_valid,
  input clk,
  input in_rst,
  output reg [2*BITWIDTH-1:0] out_d,
  output reg out_ovf,
  output reg out_d_valid,
  wire [2*BITWIDTH:0] temp
);

  assign temp = in_a * in_b + out_d;

  always @(posedge clk) begin
    if(in_rst) begin
      out_d <= 0;
      out_d_valid <= 0;
      out_ovf <= 0;
    end
    
    else begin
      if (in_a_valid & in_b_valid) begin
        out_d_valid <= 1;

        out_d <= temp[2*BITWIDTH-1:0];

        if(!out_ovf & temp[2*BITWIDTH]) begin
          out_ovf <= 1;
        end
      end
    end
  end
endmodule

Lab1/practice/top.vcd
$version Generated by VerilatedVcd $end
$date Wed Mar 15 09:26:27 2023
 $end
$timescale   1ps $end

 $scope module TOP $end
  $var wire  1 ' clk $end
  $var wire  4 # in_a [3:0] $end
  $var wire  1 $ in_a_valid $end
  $var wire  4 % in_b [3:0] $end
  $var wire  1 & in_b_valid $end
  $var wire  1 ( in_rst $end
  $var wire  8 ) out_d [7:0] $end
  $var wire  1 + out_d_valid $end
  $var wire  1 * out_ovf $end
  $var wire  9 , temp [8:0] $end
  $scope module my_mac $end
   $var wire 32 - BITWIDTH [31:0] $end
   $var wire  1 ' clk $end
   $var wire  4 # in_a [3:0] $end
   $var wire  1 $ in_a_valid $end
   $var wire  4 % in_b [3:0] $end
   $var wire  1 & in_b_valid $end
   $var wire  1 ( in_rst $end
   $var wire  8 ) out_d [7:0] $end
   $var wire  1 + out_d_valid $end
   $var wire  1 * out_ovf $end
   $var wire  9 , temp [8:0] $end
  $upscope $end
 $upscope $end
$enddefinitions $end


#0
b0000 #
0$
b0000 %
0&
0'
0(
b00000000 )
0*
0+
b000000000 ,
b00000000000000000000000000000100 -
#1
1'
#2
0'
#3
b0110 #
b0001 %
1&
1'
#4
0'
b000000110 ,
#5
b0100 #
b1101 %
0&
1'
#6
0'
b000110100 ,
#7
b0111 #
1$
b0010 %
1&
1'
#8
0'
b000001110 ,
#9
b0101 #
0$
b0000 %
0&
1'
b00001110 )
1+
b000011100 ,
#10
0'
b000001110 ,
#11
b0100 #
b1010 %
1&
1'
#12
0'
b000110110 ,
#13
b1011 #
b0001 %
1'
#14
0'
b000011001 ,
#15
b1111 #
1$
0&
1'
#16
0'
b000011101 ,
#17
b1101 #
0$
1&
1'
1(
#18
0'
b000011011 ,
#19
b0100 #
b1100 %
0&
1'
0(
b00000000 )
0+
b000001101 ,
#20
0'
b000110000 ,
#21
b1000 #
1$
b0101 %
1'
#22
0'
b000101000 ,
#23
b1001 #
b0111 %
1'
#24
0'
b000111111 ,
#25
b1111 #
b0001 %
1&
1'
#26
0'
b000001111 ,
#27
b0000 #
b1110 %
1'
b00001111 )
1+
b000011110 ,
#28
0'
b000001111 ,
#29
b1100 #
b0100 %
1'
#30
0'
b000111111 ,
#31
b1011 #
b0011 %
0&
1'
b00111111 )
b001101111 ,
#32
0'
b001100000 ,
#33
b0101 #
b1011 %
1'
1(
#34
0'
b001110110 ,
#35
b0111 #
b0010 %
1'
0(
b00000000 )
0+
b000110111 ,
#36
0'
b000001110 ,
#37
b0000 #
b0000 %
1&
1'
#38
0'
b000000000 ,
#39
b1110 #
b1000 %
1'
1+
#40
0'
b001110000 ,
#41
b0001 %
0&
1'
b01110000 )
b011100000 ,
#42
0'
b001111110 ,
#43
b0100 #
b1001 %
1'
#44
0'
b010010100 ,
#45
b1111 #
b1011 %
1'
#46
0'
b100010101 ,
#47
b0010 #
b0010 %
1'
#48
0'
b001110100 ,
#49
b0100 #
1&
1'
1(
#50
0'
b001111000 ,
#51
0$
b1011 %
0&
1'
0(
b00000000 )
0+
b000001000 ,
#52
0'
b000101100 ,
#53
b1100 #
1$
b1110 %
1'
#54
0'
b010101000 ,
#55
b0010 #
0$
b1000 %
1&
1'
#56
0'
b000010000 ,
#57
b1111 #
1$
b1111 %
1'
#58
0'
b011100001 ,
#59
b1000 #
b0100 %
1'
b11100001 )
1+
b111000010 ,
#60
0'
b100000001 ,
#61
b0110 #
b0001 %
1'
b00000001 )
1*
b000100001 ,
#62
0'
b000000111 ,
#63
b1110 #
0&
1'
b00000111 )
b000001101 ,
#64
0'
b000010101 ,
#65
b0000 #
b1110 %
1'
1(
#66
0'
b000000111 ,
#67
b0111 #
b1001 %
1&
1'
0(
b00000000 )
0*
0+
b000000000 ,
#68
0'
b000111111 ,
#69
b0101 #
b1110 %
1'
b00111111 )
1+
b001111110 ,
#70
0'
b010000101 ,
#71
b1101 #
0$
b1000 %
0&
1'
b10000101 )
b011001011 ,
#72
0'
b011101101 ,
#73
b1111 #
b1111 %
1&
1'
#74
0'
b101100110 ,
#75
b0001 #
1$
1'
#76
0'
b010010100 ,
#77
b0011 #
0$
b0000 %
1'
b10010100 )
b010100011 ,
#78
0'
b010010100 ,
#79
b0100 #
1$
b0100 %
0&
1'
#80
0'
b010100100 ,
#81
0$
b1001 %
1'
1(
#82
0'
b010111000 ,
#83
b1011 #
b1111 %
1'
0(
b00000000 )
0+
b000100100 ,
#84
0'
b010100101 ,
#85
b1001 #
1$
b1000 %
1'
#86
0'
b001001000 ,
#87
b0011 #
0$
b0010 %
1'
#88
0'
b000000110 ,
#89
b1000 #
1$
b1010 %
1&
1'
#90
0'
b001010000 ,
#91
b0101 #
b0001 %
0&
1'
b01010000 )
1+
b010100000 ,
#92
0'
b001010101 ,
#93
b1001 #
b1001 %
1&
1'
#94
0'
b010100001 ,
#95
b0011 #
b0010 %
1'
b10100001 )
b011110010 ,
#96
0'
b010100111 ,
#97
b1111 #
b0011 %
1'
1(
b10100111 )
b010101101 ,
#98
0'
b011010100 ,
#99
b1101 #
b1011 %
0&
1'
0(
b00000000 )
0+
b000101101 ,
#100
0'
b010001111 ,
#101
b0000 #
b1100 %
1'
#102
0'
b000000000 ,
#103
b0100 #
0$
b0110 %
1'
#104
0'
b000011000 ,
#105
b1111 #
1'
#106
0'
b001011010 ,
#107
b1001 #
1$
b1100 %
1&
1'
#108
0'
b001101100 ,
#109
b1000 #
0$
b0000 %
1'
b01101100 )
1+
b011011000 ,
#110
0'
b001101100 ,
#111
b0011 #
b0011 %
1'
#112
0'
b001110101 ,
#113
b1101 #
b1110 %
0&
1'
1(
#114
0'
b100100010 ,
#115
b1001 #
1$
b0000 %
1'
0(
b00000000 )
0+
b010110110 ,
#116
0'
b000000000 ,
#117
b1101 #
0$
b1110 %
1&
1'
#118
0'
b010110110 ,
#119
b1010 #
b1101 %
0&
1'
#120
0'
b010000010 ,
#121
b0101 #
1$
b1110 %
1'
#122
0'
b001000110 ,
#123
b1010 #
b0001 %
1&
1'
#124
0'
b000001010 ,
#125
b0001 #
0$
b1110 %
0&
1'
b00001010 )
1+
b000010100 ,
#126
0'
b000011000 ,
#127
b0100 #
1$
b0111 %
1'
#128
0'
b000100110 ,
#129
b1000 #
b1100 %
1&
1'
1(
#130
0'
b001101010 ,
#131
b1111 #
b1011 %
0&
1'
0(
b00000000 )
0+
b001100000 ,
#132
0'
b010100101 ,
#133
b1001 #
b1101 %
1'
#134
0'
b001110101 ,
#135
b1110 #
0$
b1110 %
1&
1'
#136
0'
b011000100 ,
#137
b0001 %
0&
1'
#138
0'
b000001110 ,
#139
b0111 #
1$
b1011 %
1'
#140
0'
b001001101 ,
#141
b0101 #
0$
b1101 %
1&
1'
#142
0'
b001000001 ,
#143
b1011 #
b1011 %
1'
#144
0'
b001111001 ,
#145
b1010 #
b0101 %
1'
1(
#146
0'
b000110010 ,
#147
b0101 #
0&
1'
0(
#148
0'
b000011001 ,
#149
b1010 #
b0010 %
1'
#150
0'
b000010100 ,
#151
b1100 #
b1011 %
1'
#152
0'
b010000100 ,
#153
b1101 #
b0011 %
1'
#154
0'
b000100111 ,
#155
b1111 #
b1101 %
1'
#156
0'
b011000011 ,
#157
b1000 #
b1110 %
1'
#158
0'
b001110000 ,
#159
b1110 #
1$
b0111 %
1'
#160
0'
b001100010 ,
#161
b0001 #
0$
b0001 %
1'
1(
#162
0'
b000000001 ,
#163
b1101 #
b0101 %
1&
1'
0(
#164
0'
b001000001 ,
#165
b1000 #
1$
b1111 %
1'
#166
0'
b001111000 ,
#167
0$
1'
b01111000 )
1+
b011110000 ,
#168
0'
#169
b0110 #
b1001 %
0&
1'
#170
0'
b010101110 ,
#171
b0001 #
b1010 %
1&
1'
#172
0'
b010000010 ,
#173
b0000 #
b1101 %
1'
#174
0'
b001111000 ,
#175
b0010 #
1$
b0111 %
1'
#176
0'
b010000110 ,
#177
b0001 #
b1010 %
0&
1'
1(
b10000110 )
b010010100 ,
#178
0'
b010010000 ,
#179
b1111 #
b0101 %
1'
0(
b00000000 )
0+
b000001010 ,
#180
0'
b001001011 ,
#181
b0110 #
0$
b1101 %
1'
#182
0'
b001001110 ,
#183
b1110 #
b0011 %
1&
1'
#184
0'
b000101010 ,
#185
b1111 #
1$
b1011 %
0&
1'
#186
0'
b010100101 ,
#187
b0011 #
b1001 %
1'
#188
0'
b000011011 ,
#189
b1110 #
b0011 %
1'
#190
0'
b000101010 ,
#191
b1100 #
0$
1&
1'
#192
0'
b000100100 ,
#193
b0011 #
1$
b1100 %
1'
1(
#194
0'
#195
b1100 #
b1011 %
1'
0(
#196
0'
b010000100 ,
#197
b0110 #
0$
b0001 %
0&
1'
b10000100 )
1+
b100001000 ,
#198
0'
b010001010 ,
#199
b0100 #
1$
b1001 %
1&
1'
#200
0'
b010101000 ,
#201
b0010 #
0$
b0011 %
1'
b10101000 )
b011001100 ,
#202
0'
b010101110 ,
#203
b1010 #
1$
b1001 %
0&
1'
#204
0'
b100000010 ,
#205
b0100 #
0$
b1000 %
1'
#206
0'
b011001000 ,
#207
b0111 #
1$
b1101 %
1'
#208
0'
b100000011 ,
#209
b1001 #
1&
1'
1(
#210
0'
b100011101 ,
#211
b1011 #
0$
b1000 %
1'
0(
b00000000 )
0+
b001110101 ,
#212
0'
b001011000 ,
#213
b0000 #
b0101 %
1'
#214
0'
b000000000 ,
#215
b1111 #
1$
b1000 %
1'
#216
0'
b001111000 ,
#217
b0011 #
0$
b0110 %
1'
b01111000 )
1+
b011110000 ,
#218
0'
b010001010 ,
#219
b1001 #
b0101 %
1'
#220
0'
b010100101 ,
#221
b1100 #
1$
b1101 %
1'
#222
0'
b100010100 ,
#223
b1001 #
0$
b1110 %
0&
1'
b00010100 )
1*
b010110000 ,
#224
0'
b010010010 ,
#225
b0100 #
1$
b0111 %
1&
1'
1(
#226
0'
b000110000 ,
#227
0$
b0000 %
0&
1'
0(
b00000000 )
0*
0+
b000011100 ,
#228
0'
b000000000 ,
#229
b1010 #
1$
b1001 %
1&
1'
#230
0'
b001011010 ,
#231
b0100 #
0$
b1010 %
0&
1'
b01011010 )
1+
b010110100 ,
#232
0'
b010000010 ,
#233
b1110 #
b0101 %
1&
1'
#234
0'
b010100000 ,
#235
b0000 #
1$
b0100 %
1'
#236
0'
b001011010 ,
#237
b1000 #
b0000 %
1'
#238
0'
#239
b1011 #
0$
b0011 %
1'
#240
0'
b001111011 ,
#241
b1010 #
1$
b1110 %
0&
1'
1(
#242
0'
b011100110 ,
#243
b1011 #
0$
b0010 %
1&
1'
0(
b00000000 )
0+
b010001100 ,
#244
0'
b000010110 ,
#245
b0100 #
b1110 %
0&
1'
#246
0'
b000111000 ,
#247
b1110 #
b0000 %
1'
#248
0'
b000000000 ,
#249
b1000 #
b0011 %
1&
1'
#250
0'
b000011000 ,
#251
b0001 #
1$
b0110 %
1'
#252
0'
b000000110 ,
#253
b1000 #
0$
b1011 %
1'
b00000110 )
1+
b000001100 ,
#254
0'
b001011110 ,
#255
b0101 #
b0011 %
1'
#256
0'
b000010101 ,
#257
b1001 #
1$
b1101 %
0&
1'
1(
